[
    {
        "id": 1,
        "UserId": 6,
        "CourseId": 1,
        "isPaid": true
    },
    {
        "id": 2,
        "UserId": 6,
        "CourseId": 2,
        "isPaid": false
    },
    {
        "id": 3,
        "UserId": 7,
        "CourseId": 1,
        "isPaid": false
    },
    {
        "id": 4,
        "UserId": 7,
        "CourseId": 5,
        "isPaid": false
    },
    {
        "id": 5,
        "UserId": 7,
        "CourseId": 6,
        "isPaid": false
    },
    {
        "id": 6,
        "UserId": 7,
        "CourseId": 10,
        "isPaid": false
    },
    {
        "id": 7,
        "UserId": 7,
        "CourseId": 12,
        "isPaid": false
    }
]